setup.py
mariposa/__init__.py
mariposa/command.py
mariposa/core.py
mariposa/dbengines.py
mariposa.egg-info/PKG-INFO
mariposa.egg-info/SOURCES.txt
mariposa.egg-info/dependency_links.txt
mariposa.egg-info/entry_points.txt
mariposa.egg-info/top_level.txt