Metadata-Version: 1.0
Name: mariposa
Version: 0.1
Summary: Safely and automatically migrate database schemas
Home-page: UNKNOWN
Author: Dan Bravender
Author-email: dan.bravender@gmail.com
License: UNKNOWN
Platform: UNKNOWN
